README
ReloadingHandler.py
setup.py
reloadinghandler.egg-info/PKG-INFO
reloadinghandler.egg-info/SOURCES.txt
reloadinghandler.egg-info/dependency_links.txt
reloadinghandler.egg-info/top_level.txt