Metadata-Version: 1.0
Name: reloadinghandler
Version: 0.1
Summary: A HTTP request handler shim
Home-page: UNKNOWN
Author: Michael Wolf
Author-email: maw@pobox.com
License: UNKNOWN
Keywords: http testing
Platform: UNKNOWN
